AUTHORS
ChangeLog
LICENSE
README.rst
requirements.txt
setup.cfg
setup.py
nessy/__init__.py
nessy_cli.egg-info/PKG-INFO
nessy_cli.egg-info/SOURCES.txt
nessy_cli.egg-info/dependency_links.txt
nessy_cli.egg-info/entry_points.txt
nessy_cli.egg-info/not-zip-safe
nessy_cli.egg-info/pbr.json
nessy_cli.egg-info/requires.txt
nessy_cli.egg-info/top_level.txt