Metadata-Version: 1.0
Name: nessy-cli
Version: 0.8.0
Summary: CLI for the Nessy Locking system
Home-page: https://github.com/genome/nessy-cli
Author: Mark Burnett
Author-email: mburnett@genome.wustl.edu
License: UNKNOWN
Platform: UNKNOWN
